generalcompute/__init__.py
generalcompute/_client.py
generalcompute/_errors.py
generalcompute/_streaming.py
generalcompute/client.py
generalcompute/resources/__init__.py
generalcompute/resources/models.py
generalcompute/resources/chat/__init__.py
generalcompute/resources/chat/completions.py
generalcompute/types/__init__.py
generalcompute/types/chat.py
generalcompute/types/models.py
generalcompute-0.2.1.dist-info/METADATA
generalcompute-0.2.1.dist-info/WHEEL
generalcompute-0.2.1.dist-info/top_level.txt
generalcompute-0.2.1.dist-info/RECORD
