Metadata-Version: 2.4
Name: generalcompute
Version: 0.2.1
Summary: OpenAI-compatible Python SDK for GeneralCompute API
Author-email: GeneralCompute <support@generalcompute.ai>
License: MIT
Project-URL: Homepage, https://generalcompute.ai
Project-URL: Documentation, https://docs.generalcompute.ai
Project-URL: Repository, https://github.com/generalcompute/sdk
Keywords: generalcompute,openai,llm,ai,sdk,api,inference,chat,completions
Classifier: Development Status :: 3 - Alpha
Classifier: Intended Audience :: Developers
Classifier: License :: OSI Approved :: MIT License
Classifier: Programming Language :: Python :: 3
Classifier: Programming Language :: Python :: 3.8
Classifier: Programming Language :: Python :: 3.9
Classifier: Programming Language :: Python :: 3.10
Classifier: Programming Language :: Python :: 3.11
Classifier: Programming Language :: Python :: 3.12
Classifier: Topic :: Software Development :: Libraries :: Python Modules
Requires-Python: >=3.8
Requires-Dist: httpx>=0.24.0
Requires-Dist: pydantic>=2.0.0
Provides-Extra: dev
Requires-Dist: pytest>=7.0.0; extra == "dev"
Requires-Dist: pytest-asyncio>=0.21.0; extra == "dev"
Requires-Dist: mypy>=1.0.0; extra == "dev"
Requires-Dist: ruff>=0.1.0; extra == "dev"
Requires-Dist: build>=1.0.0; extra == "dev"
Requires-Dist: twine>=4.0.0; extra == "dev"
